examples/__init__.py
examples/timbermill_example.py
tests/__init__.py
tests/test_timberlog.py
tests/mock/__init__.py
tests/mock/mock_rest.py
timbermill/__init__.py
timbermill/optional_args_decorator.py
timbermill/stack.py
timbermill/timberlog.py
timbermill/timberlog_consts.py
timbermill/timberlog_event_handler.py
timbermill/timberlog_mock.py
timbermill-0.0.18.dist-info/LICENSE.txt
timbermill-0.0.18.dist-info/METADATA
timbermill-0.0.18.dist-info/WHEEL
timbermill-0.0.18.dist-info/top_level.txt
timbermill-0.0.18.dist-info/RECORD
