Metadata-Version: 2.1
Name: timbermill
Version: 0.0.18
Summary: A Task-Based, Context-Aware Logging service
Home-page: https://github.com/datorama/Timbermill
Author: Shimon Klebanov
Author-email: sklebanov@salesforce.com
License: UNKNOWN
Platform: UNKNOWN
Classifier: Programming Language :: Python :: 3
Classifier: License :: OSI Approved :: Apache Software License
Classifier: Operating System :: OS Independent
Requires-Python: >=3.6
Requires-Dist: requests
